aws_portknock.py
aws_portknock-0.1.2.dist-info/AUTHORS.md
aws_portknock-0.1.2.dist-info/LICENSE
aws_portknock-0.1.2.dist-info/METADATA
aws_portknock-0.1.2.dist-info/WHEEL
aws_portknock-0.1.2.dist-info/entry_points.txt
aws_portknock-0.1.2.dist-info/top_level.txt
aws_portknock-0.1.2.dist-info/RECORD
