Metadata-Version: 2.1
Name: aws-portknock
Version: 0.1.2
Summary: Port knocking for AWS security groups
Home-page: https://github.com/michel-slm/aws-portknock
Author: Michel Lind
Author-email: michel@michel-slm.name
Keywords: aws portknock
Classifier: Development Status :: 4 - Beta
Classifier: Environment :: Console
Classifier: License :: OSI Approved :: Mozilla Public License 2.0 (MPL 2.0)
Classifier: Topic :: Security
Classifier: Topic :: Utilities
License-File: LICENSE
License-File: AUTHORS.md
Requires-Dist: boto3
Requires-Dist: click
